Workbook

Sheet Analysis
A1: NOVAHOME RETAIL (PTY) LTD
A2: Financial Performance Analysis | 2022–2026
A4: REVENUE ANALYSIS
A6: Year | B6: Total Revenue | C6: YoY Growth
A7: 2022 | B7: =SUMIF(Sales_Data!C:C,Analysis!A7,Sales_Data!H:H) -> 31077904 | C7: -
A8: 2023 | B8: =SUMIF(Sales_Data!C:C,Analysis!A8,Sales_Data!H:H) -> 37129432 | C8: =(B8-B7)/B7 -> 0.19472125
A9: 2024 | B9: =SUMIF(Sales_Data!C:C,Analysis!A9,Sales_Data!H:H) -> 43719252 | C9: =(B9-B8)/B8 -> 0.17748238
A10: 2025 | B10: =SUMIF(Sales_Data!C:C,Analysis!A10,Sales_Data!H:H) -> 51624930 | C10: =(B10-B9)/B9 -> 0.18082829
A11: 2026 | B11: =SUMIF(Sales_Data!C:C,Analysis!A11,Sales_Data!H:H) -> 61147945 | C11: =(B11-B10)/B10 -> 0.18446544
A13: Revenue By Category | B13: Column Labels
A14: Category | B14: 2022 | C14: 2023 | D14: 2024 | E14: 2025 | F14: 2026 | G14: Revenue Growth % | H14: Revenue Increase
A15: Bedroom | B15: 5904276.2 | C15: 7074690.6 | D15: 8312062.9 | E15: 9958726.7 | F15: 11655702 | G15: =(F15/B15)-1 -> 0.97411198 | H15: =F15-B15 -> 5751426.2
A16: Dining | B16: 4006546.2 | C16: 4871517.9 | D16: 5702975.3 | E16: 6678570.8 | F16: 7920075.6 | G16: =(F16/B16)-1 -> 0.97678377 | H16: =F16-B16 -> 3913529.3
A17: Home Decor | B17: 3729708.5 | C17: 4476407.1 | D17: 5245084 | E17: 6184757.5 | F17: 7252595.4 | G17: =(F17/B17)-1 -> 0.94454753 | H17: =F17-B17 -> 3522886.9
A18: Home Office | B18: 5964714.3 | C18: 7027012.7 | D18: 8173884.8 | E18: 9715851.2 | F18: 11702939 | G18: =(F18/B18)-1 -> 0.96202834 | H18: =F18-B18 -> 5738224.2
A19: Kitchen | B19: 3121468.7 | C19: 3687986.4 | D19: 4349334.6 | E19: 5161243.2 | F19: 6102670 | G19: =(F19/B19)-1 -> 0.95506367 | H19: =F19-B19 -> 2981201.3
A20: Living Room | B20: 5528178 | C20: 6643719.4 | D20: 7956312.5 | E20: 9238966 | F20: 11001983 | G20: =(F20/B20)-1 -> 0.99016442 | H20: =F20-B20 -> 5473805.1
A21: Outdoor | B21: 2823011.9 | C21: 3348098 | D21: 3979598 | E21: 4686814.2 | F21: 5511980.3 | G21: =(F21/B21)-1 -> 0.95251755 | H21: =F21-B21 -> 2688968.4
A22: Grand Total | B22: 31077904 | C22: 37129432 | D22: 43719252 | E22: 51624930 | F22: 61147945 | G22: =AVERAGE(G15:G21) -> 0.96503104
A24: Revenue By Province | B24: Column Labels
A25: Province | B25: 2022 | C25: 2023 | D25: 2024 | E25: 2025 | F25: 2026
A26: Eastern Cape | B26: 4643661.7 | C26: 5571726.8 | D26: 6492993.4 | E26: 7766774 | F26: 9143941.1 | I26: Online sales appear to be a key driver of NovaHome's revenue growth, increasing by 194% between 2022 and 2026 and growing from 28% to 42% of total revenue.
A27: Gauteng | B27: 11177494 | C27: 13316167 | D27: 15828448 | E27: 18634816 | F27: 21997398
A28: KwaZulu-Natal | B28: 6220519.7 | C28: 7437653 | D28: 8756759.5 | E28: 10330222 | F28: 12273855
A29: Western Cape | B29: 9036228.5 | C29: 10803885 | D29: 12641051 | E29: 14893118 | F29: 17732752
A30: Grand Total | B30: 31077904 | C30: 37129432 | D30: 43719252 | E30: 51624930 | F30: 61147945
A32: Revenue By Channel | B32: Column Labels
A33: Channel | B33: 2022 | C33: 2023 | D33: 2024 | E33: 2025 | F33: 2026
A34: Online | B34: 8717971.1 | C34: 11788500 | D34: 15286075 | E34: 19887692 | F34: 25613589
A35: Store | B35: 22359933 | C35: 25340932 | D35: 28433177 | E35: 31737237 | F35: 35534356
A36: Grand Total | B36: 31077904 | C36: 37129432 | D36: 43719252 | E36: 51624930 | F36: 61147945
A38: Channel | B38: 2022 Revenue | C38: 2022 Share | D38: 2026 Revenue | E38: 2026 Share | F38: Growth 22–26
A39: Online | B39: =GETPIVOTDATA("Revenue",$A$32,"Year",2022,"Channel","Online") -> 8717971.1 | C39: =B39/GETPIVOTDATA("Revenue",$B$36,"Year",2022) -> 0.28051992 | D39: =GETPIVOTDATA("Revenue",$A$32,"Year",2026,"Channel","Online") -> 25613589 | E39: =D39/GETPIVOTDATA("Revenue",$F$36,"Year",2026) -> 0.41887899 | F39: =(D39-B39)/B39 -> 1.9380218
A40: Store | B40: =GETPIVOTDATA("Revenue",$A$32,"Year",2022,"Channel","Store") -> 22359933 | C40: =B40/GETPIVOTDATA("Revenue",$B$36,"Year",2022) -> 0.71948008 | D40: =GETPIVOTDATA("Revenue",$A$32,"Year",2026,"Channel","Store") -> 35534356 | E40: =D40/GETPIVOTDATA("Revenue",$F$36,"Year",2026) -> 0.58112101 | F40: =(D40-B40)/B40 -> 0.58919781
A43: PROFITABILITY ANALYSIS
A45: Row Labels | B45: Sum of Revenue | C45: Sum of Gross_Profit | D45: Sum of EBITDA | E45: Sum of Net_Profit
A46: 2022 | B46: 31077904 | C46: 12243345 | D46: 3864772.2 | E46: 1043493.3
A47: 2023 | B47: 37129432 | C47: 14595082 | D47: 4082978.9 | E47: 1108979.7
A48: 2024 | B48: 43719252 | C48: 17210255 | D48: 4244742.1 | E48: 1144490
A49: 2025 | B49: 51624930 | C49: 20300295 | D49: 4383895.8 | E49: 1141710.4
A50: 2026 | B50: 61147945 | C50: 24066528 | D50: 4249281.1 | E50: 948376.6
A51: Grand Total | B51: 2.2469946e+08 | C51: 88415505 | D51: 20825670 | E51: 5387049.9
A53: Row Labels | B53: Sum of Revenue | C53: Sum of COGS | D53: Sum of Gross_Profit | E53: Gross Margin %
A54: Bedroom | B54: 42905459 | C54: 28280190 | D54: 14625269 | E54: =D54/B54 -> 0.34087198
A55: Dining | B55: 29179686 | C55: 18664028 | D55: 10515658 | E55: =D55/B55 -> 0.36037599
A56: Home Decor | B56: 26888553 | C56: 12903129 | D56: 13985424 | E56: =D56/B56 -> 0.52012557
A57: Home Office | B57: 42584402 | C57: 25080976 | D57: 17503425 | E57: =D57/B57 -> 0.41102903
A58: Kitchen | B58: 22422703 | C58: 12326038 | D58: 10096665 | E58: =D58/B58 -> 0.45028759
A59: Living Room | B59: 40369159 | C59: 24998204 | D59: 15370955 | E59: =D59/B59 -> 0.38075986
A60: Outdoor | B60: 20349502 | C60: 14031393 | D60: 6318109.2 | E60: =D60/B60 -> 0.31047979
A61: Grand Total | B61: 2.2469946e+08 | C61: 1.3628396e+08 | D61: 88415505
A64: MARGIN ANALYSIS
A66: Year | B66: Gross Margin | C66: EBITDA Margin | D66: Net Profit Margin | G66: EBITDA: EBITDA increased moderately from R3.9 million in 2022 to R4.2 million in 2026. However, the EBITDA margin declined consistently from 12.4% to 6.9%. This indicates that operating expenses have grown faster than gross profit, placing increasing pressure on operating profitability despite strong revenue growth.
A67: 2022 | B67: =C46/B46 -> 0.3939566 | C67: =D46/B46 -> 0.12435756 | D67: =E46/B46 -> 0.033576695 | G67: Net Profit: Despite significant revenue growth, net profit declined from R1.04 million in 2022 to R948 thousand in 2026. Net profit margin fell steadily from 3.4% to 1.6%, showing that a smaller portion of revenue is being converted into bottom-line profit as the business grows.
A68: 2023 | B68: =C47/B47 -> 0.39308659 | C68: =D47/B47 -> 0.1099661 | D68: =E47/B47 -> 0.029867942
A69: 2024 | B69: =C48/B48 -> 0.39365393 | C69: =D48/B48 -> 0.097090913 | D69: =E48/B48 -> 0.02617817
A70: 2025 | B70: =C49/B49 -> 0.39322658 | C70: =D49/B49 -> 0.084918193 | D70: =E49/B49 -> 0.022115485
A71: 2026 | B71: =C50/B50 -> 0.39357869 | C71: =D50/B50 -> 0.069491805 | D71: =E50/B50 -> 0.015509542
A74: EXPENSE ANALYSIS
A76: Sum of Amount | B76: Column Labels | I76: Revenue grew 97%
A77: Row Labels | B77: 2022 | C77: 2023 | D77: 2024 | E77: 2025 | F77: 2026 | G77: Grand Total | I77: Operating expenses grew 137%
A78: Insurance | B78: 186576.95 | C78: 234583.98 | D78: 288515.54 | E78: 349258.94 | F78: 443123.91 | G78: 1502059.3 | I78: EBITDA margin fell 12% → 7%
A79: Logistics & Delivery | B79: 1217101.5 | C79: 1521510.9 | D79: 1861211.9 | E79: 2352513.1 | F79: 2886559.5 | G79: 9838896.9 | I79: Net profit margin fell 3% → 2%
A80: Marketing & Advertising | B80: 1300376.5 | C80: 1617996.5 | D80: 1972889.2 | E80: 2451502.6 | F80: 3020213.8 | G80: 10362979
A81: Office & General | B81: 307578.73 | C81: 383449.27 | D81: 471908.21 | E81: 588655.57 | F81: 730018.24 | G81: 2481610 | I81: In terms of sales, NovaHome performed well between 2022 and 2026, with revenue increasing by 97%, from R31.1 million to R61.1 million. However, operating expenses increased by R11.4 million and grew faster than revenue at 137%. This put pressure on profitability, with the EBITDA margin declining from 12% to 7% and the net profit margin declining from 3% to 2%. Salaries and wages were the largest contributor to the increase in operating expenses, accounting for approximately 39% of the total increase.
A82: Professional Fees | B82: 252544.42 | C82: 308791.57 | D82: 380890.93 | E82: 466396.23 | F82: 581674.01 | G82: 1990297.2
A83: Rent & Occupancy | B83: 928863.07 | C83: 1168402.1 | D83: 1452709.4 | E83: 1740637.6 | F83: 2187667.3 | G83: 7478279.5
A84: Repairs & Maintenance | B84: 216851.49 | C84: 275220.07 | D84: 334228.66 | E84: 408674.83 | F84: 509970.72 | G84: 1744945.8
A85: Salaries & Wages | B85: 3253785.2 | C85: 4107525 | D85: 5104058.7 | E85: 6203127.4 | F85: 7763768.5 | G85: 26432265
A86: Technology & Software | B86: 436358.7 | C86: 542535.88 | D86: 670876.86 | E86: 831053.03 | F86: 1035765 | G86: 3516589.5
A87: Utilities | B87: 278536.63 | C87: 352087.48 | D87: 428223.75 | E87: 524579.6 | F87: 658485.86 | G87: 2241913.3
A88: Grand Total | B88: 8378573.1 | C88: 10512103 | D88: 12965513 | E88: 15916399 | F88: 19817247 | G88: 67589835
A90: Metric | B90: 2022 | C90: 2026 | D90: Growth % | E90: Column1
A91: Revenue | B91: =B7 -> 31077904 | C91: =B11 -> 61147945 | D91: =(C91-B91)/B91 -> 0.96756981 | E91: revenue increasing by 97%
A92: Operating Expenses | B92: =GETPIVOTDATA("Amount",$A$76,"Year",2022) -> 8378573.1 | C92: =GETPIVOTDATA("Amount",$A$76,"Year",2026) -> 19817247 | D92: =(C92-B92)/B92 -> 1.3652293
A94: Expense Type | B94: 2022 | C94: 2026 | D94: Increase R | E94: Growth % | G94: 2026 OpEx - 2022 OpEx
A95: Insurance | B95: =VLOOKUP(A95,A76:$G$88,2,FALSE) -> 186576.95 | C95: =VLOOKUP(A95,$A$76:$G$88,6,FALSE) -> 443123.91 | D95: =C95-B95 -> 256546.96 | E95: =(C95-B95)/B95 -> 1.3750196 | G95: =C105-B105 -> 11438674
A96: Logistics & Delivery | B96: =VLOOKUP(A96,A77:$G$88,2,FALSE) -> 1217101.5 | C96: =VLOOKUP(A96,$A$76:$G$88,6,FALSE) -> 2886559.5 | D96: =C96-B96 -> 1669458.1 | E96: =(C96-B96)/B96 -> 1.3716672 | G96: Salary_Increase/Total_OpEx_Increase
A97: Marketing & Advertising | B97: =VLOOKUP(A97,A78:$G$88,2,FALSE) -> 1300376.5 | C97: =VLOOKUP(A97,$A$76:$G$88,6,FALSE) -> 3020213.8 | D97: =C97-B97 -> 1719837.3 | E97: =(C97-B97)/B97 -> 1.3225688 | G97: =D102/D105 -> 0.39427501
A98: Office & General | B98: =VLOOKUP(A98,A79:$G$88,2,FALSE) -> 307578.73 | C98: =VLOOKUP(A98,$A$76:$G$88,6,FALSE) -> 730018.24 | D98: =C98-B98 -> 422439.5 | E98: =(C98-B98)/B98 -> 1.3734353
A99: Professional Fees | B99: =VLOOKUP(A99,A80:$G$88,2,FALSE) -> 252544.42 | C99: =VLOOKUP(A99,$A$76:$G$88,6,FALSE) -> 581674.01 | D99: =C99-B99 -> 329129.59 | E99: =(C99-B99)/B99 -> 1.3032543
A100: Rent & Occupancy | B100: =VLOOKUP(A100,A81:$G$88,2,FALSE) -> 928863.07 | C100: =VLOOKUP(A100,$A$76:$G$88,6,FALSE) -> 2187667.3 | D100: =C100-B100 -> 1258804.2 | E100: =(C100-B100)/B100 -> 1.3552097
A101: Repairs & Maintenance | B101: =VLOOKUP(A101,A82:$G$88,2,FALSE) -> 216851.49 | C101: =VLOOKUP(A101,$A$76:$G$88,6,FALSE) -> 509970.72 | D101: =C101-B101 -> 293119.23 | E101: =(C101-B101)/B101 -> 1.351705
A102: Salaries & Wages | B102: =VLOOKUP(A102,A83:$G$88,2,FALSE) -> 3253785.2 | C102: =VLOOKUP(A102,$A$76:$G$88,6,FALSE) -> 7763768.5 | D102: =C102-B102 -> 4509983.2 | E102: =(C102-B102)/B102 -> 1.3860728
A103: Technology & Software | B103: =VLOOKUP(A103,A84:$G$88,2,FALSE) -> 436358.7 | C103: =VLOOKUP(A103,$A$76:$G$88,6,FALSE) -> 1035765 | D103: =C103-B103 -> 599406.34 | E103: =(C103-B103)/B103 -> 1.3736551
A104: Utilities | B104: =VLOOKUP(A104,A85:$G$88,2,FALSE) -> 278536.63 | C104: =VLOOKUP(A104,$A$76:$G$88,6,FALSE) -> 658485.86 | D104: =C104-B104 -> 379949.22 | E104: =(C104-B104)/B104 -> 1.3640907
B105: =SUBTOTAL(109,Table14[2022]) -> 8378573.1 | C105: =SUBTOTAL(109,Table14[2026]) -> 19817247 | D105: =SUBTOTAL(109,Table14[Increase R]) -> 11438674
A107: REGIONAL ANALYSIS
A109: Province | B109: 2022 | C109: 2022 Revenue Share | D109: 2026 | E109: 2026 Revenue Share
A110: Eastern Cape | B110: 4643661.7 | C110: =B110/$B$114 -> 0.14942004 | D110: 9143941.1 | E110: =D110/$D$114 -> 0.14953799
A111: Gauteng | B111: 11177494 | C111: =B111/$B$114 -> 0.35966048 | D111: 21997398 | E111: =D111/$D$114 -> 0.35974059
A112: KwaZulu-Natal | B112: 6220519.7 | C112: =B112/$B$114 -> 0.20015892 | D112: 12273855 | E112: =D112/$D$114 -> 0.20072391
A113: Western Cape | B113: 9036228.5 | C113: =B113/$B$114 -> 0.29076055 | D113: 17732752 | E113: =D113/$D$114 -> 0.28999751
B114: =SUM(B110:B113) -> 31077904 | C114: =SUM(C110:C113) -> 1 | D114: =SUM(D110:D113) -> 61147945 | E114: =SUM(E110:E113) -> 1
A118: Sum of Revenue | B118: Column Labels | H118: Online Revenue Increase | I118: 2022 Online Share | J118: 2026 Online Share
B119: Online | D119: Online Total | E119: Store | G119: Store Total
A120: Row Labels | B120: 2022 | C120: 2026 | E120: 2022 | F120: 2026 | I120: 2022 Online Share | J120: 2022 Online Share
A121: Eastern Cape | B121: 1289709.9 | C121: 3824188.9 | D121: 5113898.8 | E121: 3353951.7 | F121: 5319752.2 | G121: 8673704 | H121: =C121-B121 -> 2534478.9 | I121: =B121/(B121+E121) -> 0.27773555 | J121: =C121/(C121+F121) -> 0.41822107
A122: Gauteng | B122: 3152229.7 | C122: 9207990.6 | D122: 12360220 | E122: 8025264.1 | F122: 12789407 | G122: 20814671 | H122: =C122-B122 -> 6055760.8 | I122: =B122/(B122+E122) -> 0.28201579 | J122: =C122/(C122+F122) -> 0.41859454
A123: KwaZulu-Natal | B123: 1757257.4 | C123: 5117119.6 | D123: 6874377.1 | E123: 4463262.3 | F123: 7156735.3 | G123: 11619998 | H123: =C123-B123 -> 3359862.2 | I123: =B123/(B123+E123) -> 0.28249367 | J123: =C123/(C123+F123) -> 0.41691218
...

Sheet Company_Info
A1: Field | B1: Value
A2: Company | B2: NovaHome Retail (Pty) Ltd
A3: Industry | B3: Retail & E-commerce
A4: Currency | B4: South African Rand (ZAR)
A5: Reporting Period | B5: January 2022 – December 2026
A6: Business Model | B6: Omnichannel homeware and lifestyle retailer
A7: Portfolio Note | B7: Fictional company and simulated data for portfolio use only

Sheet Products
A1: Product_ID | B1: Category | C1: Subcategory
A2: PR001 | B2: Living Room | C2: Sofas & Seating
A3: PR002 | B3: Living Room | C3: Coffee Tables
A4: PR003 | B4: Bedroom | C4: Beds & Bed Frames
A5: PR004 | B5: Bedroom | C5: Mattresses
A6: PR005 | B6: Dining | C6: Dining Tables
A7: PR006 | B7: Dining | C7: Dining Chairs
A8: PR007 | B8: Home Decor | C8: Decor & Accessories
A9: PR008 | B9: Kitchen | C9: Kitchenware
A10: PR009 | B10: Outdoor | C10: Outdoor Furniture
A11: PR010 | B11: Home Office | C11: Desks & Office Furniture

Sheet Regions
A1: Region_ID | B1: Province | C1: City | D1: Store
A2: R001 | B2: Gauteng | C2: Johannesburg | D2: Sandton
A3: R002 | B3: Western Cape | C3: Cape Town | D3: Century City
A4: R003 | B4: KwaZulu-Natal | C4: Durban | D4: Umhlanga
A5: R004 | B5: Eastern Cape | C5: Gqeberha | D5: Walmer

Sheet Channels
A1: Channel | B1: Channel_Type
A2: Online | B2: E-commerce
A3: Store | B3: Physical Retail

Sheet Sales_Data
A1: Order_ID | B1: Month | C1: Year | D1: Month_No | E1: Province | F1: Channel | G1: Category | H1: Revenue | I1: Units_Sold | J1: COGS | K1: Gross_Profit
A2: ORD100000 | B2: 44562 | C2: 2022 | D2: 1 | E2: Gauteng | F2: Online | G2: Living Room | H2: 43381.037 | I2: 8 | J2: 26598.829 | K2: 16782.208
A3: ORD100001 | B3: 44562 | C3: 2022 | D3: 1 | E3: Gauteng | F3: Store | G3: Living Room | H3: 99863.768 | I3: 19 | J3: 61124.491 | K3: 38739.277
A4: ORD100002 | B4: 44562 | C4: 2022 | D4: 1 | E4: Western Cape | F4: Online | G4: Living Room | H4: 30941.515 | I4: 6 | J4: 19521.757 | K4: 11419.758
A5: ORD100003 | B5: 44562 | C5: 2022 | D5: 1 | E5: Western Cape | F5: Store | G5: Living Room | H5: 80967.578 | I5: 16 | J5: 48960.394 | K5: 32007.184
A6: ORD100004 | B6: 44562 | C6: 2022 | D6: 1 | E6: KwaZulu-Natal | F6: Online | G6: Living Room | H6: 23938.204 | I6: 5 | J6: 15271.473 | K6: 8666.7312
A7: ORD100005 | B7: 44562 | C7: 2022 | D7: 1 | E7: KwaZulu-Natal | F7: Store | G7: Living Room | H7: 58179.319 | I7: 11 | J7: 36608.932 | K7: 21570.387
A8: ORD100006 | B8: 44562 | C8: 2022 | D8: 1 | E8: Eastern Cape | F8: Online | G8: Living Room | H8: 16540.103 | I8: 3 | J8: 10456.223 | K8: 6083.8797
A9: ORD100007 | B9: 44562 | C9: 2022 | D9: 1 | E9: Eastern Cape | F9: Store | G9: Living Room | H9: 40863.225 | I9: 8 | J9: 25124.084 | K9: 15739.141
A10: ORD100008 | B10: 44562 | C10: 2022 | D10: 1 | E10: Gauteng | F10: Online | G10: Bedroom | H10: 40914.9 | I10: 7 | J10: 26930.952 | K10: 13983.948
A11: ORD100009 | B11: 44562 | C11: 2022 | D11: 1 | E11: Gauteng | F11: Store | G11: Bedroom | H11: 103339.87 | I11: 17 | J11: 66444.869 | K11: 36895.006
A12: ORD100010 | B12: 44562 | C12: 2022 | D12: 1 | E12: Western Cape | F12: Online | G12: Bedroom | H12: 28009.85 | I12: 5 | J12: 18311.916 | K12: 9697.9341
A13: ORD100011 | B13: 44562 | C13: 2022 | D13: 1 | E13: Western Cape | F13: Store | G13: Bedroom | H13: 82210.373 | I13: 13 | J13: 54740.979 | K13: 27469.394
... A3361: ORD103359 | B3361: 46357 | C3361: 2026 | D3361: 12 | E3361: Eastern Cape | F3361: Store | G3361: Home Office | H3361: 102016.71 | I3361: 29 | J3361: 58587.272 | K3361: 43429.438

Sheet Expenses_Data
A1: Month | B1: Year | C1: Month_No | D1: Expense_Type | E1: Department | F1: Amount
A2: 44562 | B2: 2022 | C2: 1 | D2: Salaries & Wages | E2: Personnel | F2: 218018.28 | H2: One row represents a specific type of operating expense incurred by a particular department in a particular month.
A3: 44562 | B3: 2022 | C3: 1 | D3: Rent & Occupancy | E3: Facilities | F3: 62175.127
A4: 44562 | B4: 2022 | C4: 1 | D4: Marketing & Advertising | E4: Sales & Marketing | F4: 84448.416
A5: 44562 | B5: 2022 | C5: 1 | D5: Technology & Software | E5: Technology | F5: 28356.85
A6: 44562 | B6: 2022 | C6: 1 | D6: Logistics & Delivery | E6: Operations | F6: 75199.835
A7: 44562 | B7: 2022 | C7: 1 | D7: Utilities | E7: Facilities | F7: 18695.276
A8: 44562 | B8: 2022 | C8: 1 | D8: Insurance | E8: Administration | F8: 12502.13
A9: 44562 | B9: 2022 | C9: 1 | D9: Professional Fees | E9: Administration | F9: 17169.563
A10: 44562 | B10: 2022 | C10: 1 | D10: Office & General | E10: Administration | F10: 20034.267
A11: 44562 | B11: 2022 | C11: 1 | D11: Repairs & Maintenance | E11: Operations | F11: 14902.098
A12: 44593 | B12: 2022 | C12: 2 | D12: Salaries & Wages | E12: Personnel | F12: 221814.17
A13: 44593 | B13: 2022 | C13: 2 | D13: Rent & Occupancy | E13: Facilities | F13: 59269.088
A14: 44593 | B14: 2022 | C14: 2 | D14: Marketing & Advertising | E14: Sales & Marketing | F14: 77204.144
... A601: 46357 | B601: 2026 | C601: 12 | D601: Repairs & Maintenance | E601: Operations | F601: 52441.379

Sheet Income_Statement
A1: Month | B1: Year | C1: Month_No | D1: Revenue | E1: Cost_of_Sales | F1: Gross_Profit | G1: Operating_Expenses | H1: EBITDA | I1: Depreciation | J1: Operating_Profit | K1: Interest_Expense | L1: Profit_Before_Tax | M1: Tax | N1: Net_Profit
A2: 44562 | B2: 2022 | C2: 1 | D2: 2131660 | E2: 1290161.5 | F2: 841498.43 | G2: 551501.84 | H2: 289996.58 | I2: 153061.88 | J2: 136934.7 | K2: 47347.307 | L2: 89587.391 | M2: 24188.596 | N2: 65398.796
A3: 44593 | B3: 2022 | C3: 2 | D3: 2070207.2 | E3: 1255932.1 | F3: 814275.13 | G3: 541054.96 | H3: 273220.16 | I3: 153149.37 | J3: 120070.8 | K3: 48184.214 | L3: 71886.582 | M3: 19409.377 | N3: 52477.205
A4: 44621 | B4: 2022 | C4: 3 | D4: 2307904.1 | E4: 1401969.3 | F4: 905934.75 | G4: 608944.42 | H4: 296990.33 | I4: 154626.7 | J4: 142363.63 | K4: 47466.925 | L4: 94896.704 | M4: 25622.11 | N4: 69274.594
A5: 44652 | B5: 2022 | C5: 4 | D5: 2409981 | E5: 1462931.3 | F5: 947049.67 | G5: 630480.36 | H5: 316569.31 | I5: 155995.01 | J5: 160574.3 | K5: 49654.152 | L5: 110920.15 | M5: 29948.439 | N5: 80971.706
A6: 44682 | B6: 2022 | C6: 5 | D6: 2596867.5 | E6: 1567592.1 | F6: 1029275.4 | G6: 687385.02 | H6: 341890.39 | I6: 158811.27 | J6: 183079.12 | K6: 46154.139 | L6: 136924.98 | M6: 36969.745 | N6: 99955.236
A7: 44713 | B7: 2022 | C7: 6 | D7: 2535494.6 | E7: 1538794.9 | F7: 996699.66 | G7: 683063.43 | H7: 313636.23 | I7: 156341.69 | J7: 157294.54 | K7: 47829.098 | L7: 109465.44 | M7: 29555.669 | N7: 79909.771
A8: 44743 | B8: 2022 | C8: 7 | D8: 2528901.4 | E8: 1529725.6 | F8: 999175.8 | G8: 689978.65 | H8: 309197.15 | I8: 155360.74 | J8: 153836.42 | K8: 47617.648 | L8: 106218.77 | M8: 28679.068 | N8: 77539.701
A9: 44774 | B9: 2022 | C9: 8 | D9: 2433091.9 | E9: 1474398.6 | F9: 958693.3 | G9: 639969.55 | H9: 318723.75 | I9: 155273.39 | J9: 163450.36 | K9: 48145.351 | L9: 115305.01 | M9: 31132.352 | N9: 84172.655
A10: 44805 | B10: 2022 | C10: 9 | D10: 2569747.3 | E10: 1553944.3 | F10: 1015803.1 | G10: 694551.42 | H10: 321251.63 | I10: 153653.94 | J10: 167597.69 | K10: 47139.487 | L10: 120458.2 | M10: 32523.715 | N10: 87934.488
A11: 44835 | B11: 2022 | C11: 10 | D11: 2855531.1 | E11: 1725337.5 | F11: 1130193.6 | G11: 743834.82 | H11: 386358.81 | I11: 153956.78 | J11: 232402.02 | K11: 48224.889 | L11: 184177.14 | M11: 49727.826 | N11: 134449.31
A12: 44866 | B12: 2022 | C12: 11 | D12: 3307858.3 | E12: 2009798.7 | F12: 1298059.6 | G12: 947500.15 | H12: 350559.45 | I12: 156392.67 | J12: 194166.78 | K12: 48819.215 | L12: 145347.56 | M12: 39243.843 | N12: 106103.72
A13: 44896 | B13: 2022 | C13: 12 | D13: 3330659.3 | E13: 2023972.4 | F13: 1306686.9 | G13: 960308.47 | H13: 346378.43 | I13: 153851.01 | J13: 192527.42 | K13: 48272.491 | L13: 144254.93 | M13: 38948.832 | N13: 105306.1
... A61: 46357 | B61: 2026 | C61: 12 | D61: 6294204.3 | E61: 3819099.1 | F61: 2475105.1 | G61: 2174978.4 | H61: 300126.72 | I61: 190032.99 | J61: 110093.73 | K61: 54529.757 | L61: 55563.973 | M61: 15002.273 | N61: 40561.7

Sheet Annual_Summary
A1: Year | B1: Month_No | C1: Revenue | D1: Cost_of_Sales | E1: Gross_Profit | F1: Operating_Expenses | G1: EBITDA | H1: Depreciation | I1: Operating_Profit | J1: Interest_Expense | K1: Profit_Before_Tax | L1: Tax | M1: Net_Profit | N1: Gross_Margin | O1: EBITDA_Margin | P1: Net_Profit_Margin | Q1: Revenue_Growth | R1: Profit_Growth | S1: Expense_Growth
A2: 2022 | B2: 78 | C2: 31077904 | D2: 18834558 | E2: 12243345 | F2: 8378573.1 | G2: 3864772.2 | H2: 1860474.5 | I2: 2004297.8 | J2: 574854.92 | K2: 1429442.9 | L2: 385949.57 | M2: 1043493.3 | N2: 0.3939566 | O2: 0.12435756 | P2: 0.033576695
A3: 2023 | B3: 78 | C3: 37129432 | D3: 22534350 | E3: 14595082 | F3: 10512103 | G3: 4082978.9 | H3: 1970848.4 | I3: 2112130.5 | J3: 592980.23 | K3: 1519150.3 | L3: 410170.58 | M3: 1108979.7 | N3: 0.39308659 | O3: 0.1099661 | P3: 0.029867942 | Q3: 0.19472125 | R3: 0.062756926 | S3: 0.25464118
A4: 2024 | B4: 78 | C4: 43719252 | D4: 26508997 | E4: 17210255 | F4: 12965513 | G4: 4244742.1 | H4: 2065221.5 | I4: 2179520.6 | J4: 611726.12 | K4: 1567794.5 | L4: 423304.52 | M4: 1144490 | N4: 0.39365393 | O4: 0.097090913 | P4: 0.02617817 | Q4: 0.17748238 | R4: 0.032020673 | S4: 0.23338911
A5: 2025 | B5: 78 | C5: 51624930 | D5: 31324635 | E5: 20300295 | F5: 15916399 | G5: 4383895.8 | H5: 2193410.1 | I5: 2190485.6 | J5: 626498.83 | K5: 1563986.8 | L5: 422276.43 | M5: 1141710.4 | N5: 0.39322658 | O5: 0.084918193 | P5: 0.022115485 | Q5: 0.18082829 | R5: -0.0024287078 | S5: 0.22759497
A6: 2026 | B6: 78 | C6: 61147945 | D6: 37081417 | E6: 24066528 | F6: 19817247 | G6: 4249281.1 | H6: 2303302.7 | I6: 1945978.3 | J6: 646832.29 | K6: 1299146 | L6: 350769.43 | M6: 948376.6 | N6: 0.39357869 | O6: 0.069491805 | P6: 0.015509542 | Q6: 0.18446544 | R6: -0.16933696 | S6: 0.24508358

Sheet Balance_Sheet
A1: Year | B1: Cash | C1: Trade_Receivables | D1: Inventory | E1: Property_Plant_Equipment | F1: Total_Assets | G1: Trade_Payables | H1: Short_Term_Debt | I1: Long_Term_Debt | J1: Total_Liabilities | K1: Total_Equity | L1: Current_Assets | M1: Current_Liabilities | N1: Current_Ratio | O1: Debt_to_Equity
A2: 2022 | B2: 3921593.1 | C2: 1769337.1 | D2: 2788781.2 | E2: 5958142.3 | F2: 14437854 | G2: 1540587 | H2: 1200000 | I2: 3500000 | J2: 6240587 | K2: 8197266.8 | L2: 8479711.4 | M2: 2740587 | N2: 3.0941223 | O2: 0.57336184
A3: 2023 | B3: 4486977 | C3: 2078921.8 | D3: 3179731 | E3: 6288254.5 | F3: 16033884 | G3: 1863346.3 | H3: 1152000 | I3: 3290000 | J3: 6305346.3 | K3: 9728538 | L3: 9745629.8 | M3: 3015346.3 | N3: 3.2320101 | O3: 0.45659481
A4: 2024 | B4: 5207926.6 | C4: 2297464.3 | D4: 3812168.6 | E4: 6629901.4 | F4: 17947461 | G4: 2294382.3 | H4: 1105920 | I4: 3092600 | J4: 6492902.3 | K4: 11454559 | L4: 11317559 | M4: 3400302.3 | N4: 3.328398 | O4: 0.36653704
A5: 2025 | B5: 5802251.3 | C5: 2955231.8 | D5: 4439305.8 | E5: 6998926.5 | F5: 20195715 | G5: 2647441.7 | H5: 1061683.2 | I5: 2907044 | J5: 6616168.9 | K5: 13579546 | L5: 13196789 | M5: 3709124.9 | N5: 3.5579252 | O5: 0.29225771
A6: 2026 | B6: 6047890.8 | C6: 3607177.4 | D6: 4931222.1 | E6: 7380643.9 | F6: 21966934 | G6: 3293327.4 | H6: 1019215.9 | I6: 2732621.4 | J6: 7045164.7 | K6: 14921770 | L6: 14586290 | M6: 4312543.3 | N6: 3.3822942 | O6: 0.2514338

Sheet Cash_Flow
A1: Year | B1: Operating_Cash_Flow | C1: Capital_Expenditure | D1: Financing_Cash_Flow | E1: Net_Change_in_Cash
A2: 2022 | B2: 2830130.7 | C2: -1000000 | D2: -450000 | E2: 1380130.7
A3: 2023 | B3: 2996454.5 | C3: -1060000 | D3: -436500 | E3: 1499954.5
A4: 2024 | B4: 3114351.8 | C4: -1123600 | D4: -423000 | E4: 1567751.8
A5: 2025 | B5: 3218597.6 | C5: -1191016 | D5: -409500 | E5: 1618081.6
A6: 2026 | B6: 3122749.5 | C6: -1262477 | D6: -396000 | E6: 1464272.5

Sheet Category_Performance
A1: Year | B1: Category | C1: Revenue | D1: COGS | E1: Units_Sold | F1: Gross_Profit | G1: Gross_Margin
A2: 2022 | B2: Bedroom | C2: 5904276.2 | D2: 3891933.3 | E2: 969 | F2: 2012342.9 | G2: 0.34082804
A3: 2022 | B3: Dining | C3: 4006546.2 | D3: 2558177.1 | E3: 930 | F3: 1448369.1 | G3: 0.36150067
A4: 2022 | B4: Home Decor | C4: 3729708.5 | D4: 1783564.3 | E4: 4389 | F4: 1946144.2 | G4: 0.52179526
A5: 2022 | B5: Home Office | C5: 5964714.3 | D5: 3521351 | E5: 1700 | F5: 2443363.3 | G5: 0.40963627
A6: 2022 | B6: Kitchen | C6: 3121468.7 | D6: 1714385 | E6: 4337 | F6: 1407083.7 | G6: 0.45077617
A7: 2022 | B7: Living Room | C7: 5528178 | D7: 3425586.7 | E7: 1065 | F7: 2102591.2 | G7: 0.38034073
A8: 2022 | B8: Outdoor | C8: 2823011.9 | D8: 1939561.1 | E8: 522 | F8: 883450.83 | G8: 0.31294619
A9: 2023 | B9: Bedroom | C9: 7074690.6 | D9: 4668428.3 | E9: 1162 | F9: 2406262.3 | G9: 0.34012262
A10: 2023 | B10: Dining | C10: 4871517.9 | D10: 3125189.7 | E10: 1132 | F10: 1746328.2 | G10: 0.35847721
A11: 2023 | B11: Home Decor | C11: 4476407.1 | D11: 2149467.1 | E11: 5265 | F11: 2326940 | G11: 0.51982314
A12: 2023 | B12: Home Office | C12: 7027012.7 | D12: 4138368.7 | E12: 2002 | F12: 2888643.9 | G12: 0.41107709
A13: 2023 | B13: Kitchen | C13: 3687986.4 | D13: 2034001.4 | E13: 5126 | F13: 1653985 | G13: 0.44847915
... A36: 2026 | B36: Outdoor | C36: 5511980.3 | D36: 3811562.2 | E36: 1026 | F36: 1700418.1 | G36: 0.30849495

Sheet Regional_Performance
A1: Year | B1: Province | C1: Revenue | D1: COGS | E1: Units_Sold | F1: Gross_Profit | G1: Gross_Margin
A2: 2022 | B2: Eastern Cape | C2: 4643661.7 | D2: 2824915.8 | E2: 2067 | F2: 1818745.9 | G2: 0.39166201
A3: 2022 | B3: Gauteng | C3: 11177494 | D3: 6776371.8 | E3: 4999 | F3: 4401122.1 | G3: 0.39374855
A4: 2022 | B4: KwaZulu-Natal | C4: 6220519.7 | D4: 3765341.1 | E4: 2788 | F4: 2455178.7 | G4: 0.39469028
A5: 2022 | B5: Western Cape | C5: 9036228.5 | D5: 5467929.7 | E5: 4058 | F5: 3568298.8 | G5: 0.39488806
A6: 2023 | B6: Eastern Cape | C6: 5571726.8 | D6: 3380901.5 | E6: 2492 | F6: 2190825.3 | G6: 0.39320401
A7: 2023 | B7: Gauteng | C7: 13316167 | D7: 8090349.6 | E7: 5950 | F7: 5225817.5 | G7: 0.39244157
A8: 2023 | B8: KwaZulu-Natal | C8: 7437653 | D8: 4521375 | E8: 3322 | F8: 2916278 | G8: 0.39209654
A9: 2023 | B9: Western Cape | C9: 10803885 | D9: 6541724.3 | E9: 4820 | F9: 4262161 | G9: 0.39450262
A10: 2024 | B10: Eastern Cape | C10: 6492993.4 | D10: 3938891.8 | E10: 2895 | F10: 2554101.5 | G10: 0.39336272
A11: 2024 | B11: Gauteng | C11: 15828448 | D11: 9593120.3 | E11: 7078 | F11: 6235328 | G11: 0.39393173
A12: 2024 | B12: KwaZulu-Natal | C12: 8756759.5 | D12: 5312371.8 | E12: 3915 | F12: 3444387.6 | G12: 0.39334044
A13: 2024 | B13: Western Cape | C13: 12641051 | D13: 7664612.8 | E13: 5620 | F13: 4976438.1 | G13: 0.39367282
... A21: 2026 | B21: Western Cape | C21: 17732752 | D21: 10731045 | E21: 7904 | F21: 7001706.5 | G21: 0.39484602

Sheet Assumptions
A1: Assumption | B1: Value | C1: Comment
A2: Reporting period | B2: 2022-2026 | C2: Five-year historical analysis
A3: Currency | B3: ZAR | C3: All monetary values are South African Rand
A4: Tax rate | B4: 0.27 | C4: Illustrative corporate tax assumption
A5: Online channel | B5: Increasing | C5: Online share rises over the period
A6: Gross margin | B6: Category-driven | C6: COGS varies by product category
A7: Seasonality | B7: Higher Nov-Dec | C7: Retail peak around year-end
A8: Data status | B8: Simulated | C8: Entire dataset is fictional and created for portfolio practice
